panda3d_viewer/__init__.py
panda3d_viewer/geometry.py
panda3d_viewer/viewer.py
panda3d_viewer/viewer_app.py
panda3d_viewer/viewer_config.py
panda3d_viewer/viewer_errors.py
panda3d_viewer/viewer_proxy.py
tests/__init__.py
tests/test_import.py
panda3d_viewer-0.4.1.dist-info/LICENSE
panda3d_viewer-0.4.1.dist-info/METADATA
panda3d_viewer-0.4.1.dist-info/WHEEL
panda3d_viewer-0.4.1.dist-info/top_level.txt
panda3d_viewer-0.4.1.dist-info/RECORD
