Metadata-Version: 2.1
Name: panda3d-viewer
Version: 0.4.1
Summary: Easy-to-use python 3D graphics viewer
Home-page: https://github.com/ikalevatykh/panda3d_viewer
Author: Igor Kalevatykh
Author-email: kalevatykhia@gmail.com
License: MIT
Keywords: rendering graphics 3d visualization
Platform: UNKNOWN
Classifier: Development Status :: 4 - Beta
Classifier: License :: OSI Approved :: MIT License
Classifier: Operating System :: POSIX :: Linux
Classifier: Operating System :: MacOS :: MacOS X
Classifier: Programming Language :: Python :: 2.7
Classifier: Programming Language :: Python :: 3.5
Classifier: Programming Language :: Python :: 3.6
Classifier: Programming Language :: Python :: 3.7
Classifier: Programming Language :: Python :: 3.8
Classifier: Programming Language :: Python :: Implementation :: PyPy
Classifier: Topic :: Scientific/Engineering
Requires-Dist: numpy
Requires-Dist: panda3d (>=1.10)
